odoo_tools/__init__.py
odoo_tools/compat.py
odoo_tools/db.py
odoo_tools/entrypoints.py
odoo_tools/env.py
odoo_tools/exceptions.py
odoo_tools/odoo.py
odoo_tools/patch.py
odoo_tools/utils.py
odoo_tools/api/__init__.py
odoo_tools/api/context.py
odoo_tools/api/db.py
odoo_tools/api/environment.py
odoo_tools/api/management.py
odoo_tools/api/modules.py
odoo_tools/api/objects.py
odoo_tools/api/services.py
odoo_tools/app/__init__.py
odoo_tools/app/application.py
odoo_tools/app/utils.py
odoo_tools/app/mixins/__init__.py
odoo_tools/app/mixins/app.py
odoo_tools/app/mixins/dispatchers.py
odoo_tools/app/mixins/http.py
odoo_tools/app/mixins/request.py
odoo_tools/app/mixins/routers.py
odoo_tools/app/mixins/routing.py
odoo_tools/app/mixins/sessions.py
odoo_tools/app/plugins/__init__.py
odoo_tools/app/plugins/base.py
odoo_tools/app/plugins/logging.py
odoo_tools/cli/__init__.py
odoo_tools/cli/odot.py
odoo_tools/cli/registry.py
odoo_tools/cli/click/__init__.py
odoo_tools/cli/click/config.py
odoo_tools/cli/click/db.py
odoo_tools/cli/click/entrypoint.py
odoo_tools/cli/click/gen.py
odoo_tools/cli/click/manage.py
odoo_tools/cli/click/module.py
odoo_tools/cli/click/path.py
odoo_tools/cli/click/platform.py
odoo_tools/cli/click/services.py
odoo_tools/cli/click/shell.py
odoo_tools/cli/click/users.py
odoo_tools/cli/click/utils.py
odoo_tools/configuration/__init__.py
odoo_tools/configuration/git.py
odoo_tools/configuration/misc.py
odoo_tools/configuration/odoo.py
odoo_tools/configuration/pip.py
odoo_tools/docker/__init__.py
odoo_tools/docker/sudo_entrypoint.py
odoo_tools/docker/user_entrypoint.py
odoo_tools/modules/__init__.py
odoo_tools/modules/assets.py
odoo_tools/modules/render.py
odoo_tools/modules/search.py
odoo_tools/modules/translate.py
odoo_tools/overlays/common/odoo/http.py
odoo_tools/overlays/common/odoo/__pycache__/http.cpython-38.pyc
odoo_tools/overlays/common/odoo/addons/base/models/ir_http.py
odoo_tools/overlays/common/odoo/addons/base/models/__pycache__/ir_http.cpython-38.pyc
odoo_tools-0.1.9.dist-info/LICENSE.txt
odoo_tools-0.1.9.dist-info/METADATA
odoo_tools-0.1.9.dist-info/WHEEL
odoo_tools-0.1.9.dist-info/entry_points.txt
odoo_tools-0.1.9.dist-info/top_level.txt
odoo_tools-0.1.9.dist-info/RECORD
