Metadata-Version: 2.1
Name: odoo-tools
Version: 0.1.9
Summary: Odoo Tools
Home-page: https://odoo-tools.readthedocs.io
Author: Loïc Faure-Lacroix <lamerstar@gmail.com>
Author-email: lamerstar@gmail.com
License: GPL3
Project-URL: Source, https://github.com/llacroix/odoo-tools
Project-URL: Documentation, https://odoo-tools.readthedocs.io
Platform: UNKNOWN
Classifier: Programming Language :: Python :: 3
Classifier: License :: OSI Approved :: MIT License
Classifier: Operating System :: OS Independent
Requires-Python: >=3.6
License-File: LICENSE.txt
Requires-Dist: giturlparse
Requires-Dist: toposort
Requires-Dist: toml
Requires-Dist: requests
Requires-Dist: packaging
Requires-Dist: lxml
Requires-Dist: docutils
Requires-Dist: distro
Requires-Dist: polib
Requires-Dist: six (>=1.12.0)
Requires-Dist: cryptography
Requires-Dist: click
Requires-Dist: passlib
Requires-Dist: ptpython
Requires-Dist: pip (>=10.0)
Requires-Dist: password-strength
Requires-Dist: psycopg2
Requires-Dist: overlaymodule
Provides-Extra: docs
Requires-Dist: sphinx ; extra == 'docs'
Requires-Dist: furo ; extra == 'docs'
Requires-Dist: sphinx-argparse ; extra == 'docs'
Requires-Dist: sphinx-click ; extra == 'docs'
Requires-Dist: sphinxcontrib.asciinema ; extra == 'docs'
Provides-Extra: test
Requires-Dist: mock ; extra == 'test'
Requires-Dist: pytest ; extra == 'test'
Requires-Dist: pytest-cov ; extra == 'test'
